client/AddonClient.py
client/AuthClient.py
client/BillingClient.py
client/ComputeClient.py
client/DomainClient.py
client/__init__.py
lumaserv_api_client-0.0.3.dist-info/LICENSE
lumaserv_api_client-0.0.3.dist-info/METADATA
lumaserv_api_client-0.0.3.dist-info/WHEEL
lumaserv_api_client-0.0.3.dist-info/top_level.txt
lumaserv_api_client-0.0.3.dist-info/RECORD
